grafana_snapshots/__init__.py
grafana_snapshots/cli.py
grafana_snapshots/constants.py
grafana_snapshots/grafana.py
grafana_snapshots/grafanaData.py
grafana_snapshots/conf/grafana-snapshots.yml
grafana_snapshots/dataresults/__init__.py
grafana_snapshots/dataresults/dataresults.py
grafana_snapshots/dataresults/resultsBase.py
grafana_snapshots/dataresults/resultsFrame.py
grafana_snapshots/dataresults/resultsGraphite.py
grafana_snapshots/dataresults/resultsInfluxDB.py
grafana_snapshots/dataresults/resultsMatrix.py
grafana_snapshots/dataresults/resultsSQL.py
grafana_snapshots/dataresults/resultsStream.py
grafana_snapshots/dataresults/panels/__init__.py
grafana_snapshots/dataresults/panels/default.py
grafana_snapshots/dataresults/panels/dispatcher.py
grafana_snapshots/dataresults/panels/graph.py
grafana_snapshots/dataresults/panels/stat.py
grafana_snapshots/dataresults/panels/table.py
grafana_snapshots/dataresults/panels/timeseries.py
grafana_snapshots-0.3.1.dist-info/licenses/LICENSE
grafana_snapshots-0.3.1.dist-info/METADATA
grafana_snapshots-0.3.1.dist-info/WHEEL
grafana_snapshots-0.3.1.dist-info/entry_points.txt
grafana_snapshots-0.3.1.dist-info/top_level.txt
grafana_snapshots-0.3.1.dist-info/RECORD
